{"key":"idp/adapter/AuthorizationCode/-BAWMkEk64kox5xfjMtmNTUCMGvRWJG4StAVDqJ_hyN","payload":{"payload":{"iat":1722574493,"exp":1722575093,"accountId":"http://localhost:3000/alice/profile/card#me","authTime":1722567978,"codeChallenge":"yHJchxluqXcAa6M6VLgvkPRBW5kJ86_dfcmvLY69Ips","codeChallengeMethod":"S256","grantId":"YqeaSHyeNJFydodlQMXIKHed69p-2V5SUWJn3nHOhgE","redirectUri":"http://localhost:4200/redirect","resource":"http://example.com/","scope":"openid webid ","sessionUid":"zJln_qVpFPvXg2RR_KLi6","kind":"AuthorizationCode","jti":"-BAWMkEk64kox5xfjMtmNTUCMGvRWJG4StAVDqJ_hyN","clientId":"http://localhost:4200/id-local.jsonld","expiresWithSession":true,"consumed":1722574494}}}