{"key":"idp/adapter/AuthorizationCode/-ECZ7-Ywqs7MF8V2_MRkVdeGST3ZiOnycyybwC4Am9t","payload":{"payload":{"iat":1722567981,"exp":1722568581,"accountId":"http://localhost:3000/bob/profile/card#me","authTime":1722567630,"codeChallenge":"VKVLLUQlPXpku0nqIjroV_2I3wAQZOhRSQJ4RPqlTas","codeChallengeMethod":"S256","grantId":"r3l4Z_6Uuf_kQs-AP8D7bIDZdVuoqOXzbFBzXPRuuGf","redirectUri":"http://localhost:4200/redirect","resource":"http://example.com/","scope":"openid webid ","sessionUid":"ovCHuBHQqpVzw3RCZBe3I","kind":"AuthorizationCode","jti":"-ECZ7-Ywqs7MF8V2_MRkVdeGST3ZiOnycyybwC4Am9t","clientId":"http://localhost:4200/id-local.jsonld","expiresWithSession":true,"consumed":1722567981}}}