{"key":"idp/adapter/AuthorizationCode/aWqGVhNvor_v0IsR9LvhDS1uf6hvibaq4Gh2FOruWMG","payload":{"payload":{"iat":1712263676,"exp":1712264276,"accountId":"http://localhost:3000/alice/profile/card#me","authTime":1712263676,"codeChallenge":"elvCfFLnM5_Sn54HSvBcuceAYAGKveBO2pd2IlaxX98","codeChallengeMethod":"S256","grantId":"Op-uLpwm2oOuTWA4W6jvagXU9MQz6KYoKkEzzsUAOma","redirectUri":"http://localhost:4500/redirect","resource":"http://example.com/","scope":"openid offline_access webid ","sessionUid":"Cvl1AT_OB8xm2OIMwvxsu","kind":"AuthorizationCode","jti":"aWqGVhNvor_v0IsR9LvhDS1uf6hvibaq4Gh2FOruWMG","clientId":"http://localhost:3000/acme/projectron/vue","consumed":1712263676}}}