{"key":"idp/adapter/AuthorizationCode/cS0KIJeaMIodr_s6qYXFKidT2ORTpVHuqC4NkkIgVwa","payload":{"payload":{"iat":1716231791,"exp":1716232391,"accountId":"http://localhost:3000/alice/profile/card#me","authTime":1716231412,"codeChallenge":"wxAA90_0JiRqWMZzYaH-sd8Jt_6xPEmNsMJh5f8NwQs","codeChallengeMethod":"S256","grantId":"xTQH-Wq7uI9IgtVAxBQS_pxBGRwnBDtChxpTMAegWsG","redirectUri":"http://localhost:4500/redirect","resource":"http://example.com/","scope":"openid webid ","sessionUid":"rYC5jQpyRoo3ObRLa3swB","kind":"AuthorizationCode","jti":"cS0KIJeaMIodr_s6qYXFKidT2ORTpVHuqC4NkkIgVwa","clientId":"http://localhost:3000/acme/projectron/vue","expiresWithSession":true,"consumed":1716231792}}}