{"key":"idp/adapter/AuthorizationCode/kp9HGfkjSRzWX6oCX_AHgLHpP419LxxRGDdoTF8q7iv","payload":{"payload":{"iat":1722886538,"exp":1722887138,"accountId":"http://localhost:3000/bob/profile/card#me","authTime":1722886538,"codeChallenge":"gYZDt6dLxY4ngboqgXUZ38PrKX3s7WZbfphQOeG3e2s","codeChallengeMethod":"S256","grantId":"vPbYis9nP5SL8b4EJSRihhJXyElsaHTbRJ0FbNhcKSB","redirectUri":"http://localhost:4500/redirect","resource":"http://example.com/","scope":"openid offline_access webid ","sessionUid":"xDqC-PvOQCAJgC9d9cVif","kind":"AuthorizationCode","jti":"kp9HGfkjSRzWX6oCX_AHgLHpP419LxxRGDdoTF8q7iv","clientId":"http://localhost:3000/acme/projectron/vue","consumed":1722886539}}}