{"key":"idp/adapter/AuthorizationCode/KpI6SvJseHVtBoEi0dBO3zVAo5k7q3IEQKdXDpZDxze","payload":{"payload":{"iat":1721673780,"exp":1721674380,"accountId":"http://localhost:3000/alice/profile/card#me","authTime":1721670382,"codeChallenge":"MN6_TSsPLLdfmKuL2l9z5W1hpRwuELojW8Yn5sKlpdo","codeChallengeMethod":"S256","grantId":"RnyTDXELfApSCqkewZbFotuji261Bra58bW3dqEZpQO","redirectUri":"http://localhost:4500/redirect","resource":"http://example.com/","scope":"openid webid ","sessionUid":"j6CwEOZPJI2kU7mKFcKTF","kind":"AuthorizationCode","jti":"KpI6SvJseHVtBoEi0dBO3zVAo5k7q3IEQKdXDpZDxze","clientId":"http://localhost:3000/acme/projectron/vue","expiresWithSession":true,"consumed":1721673782}}}