{"key":"idp/adapter/AuthorizationCode/q-txnZcaFNmL8ztjR3ptYwEvuDt9AZkS0yDjXmfgiti","payload":{"payload":{"iat":1722800477,"exp":1722801077,"accountId":"http://localhost:3000/alice/profile/card#me","authTime":1722800477,"codeChallenge":"M4iG44kB2cpmVCz2frGezbaJJdeUh4XJUmwARQw7j4I","codeChallengeMethod":"S256","grantId":"RBAP9h9OLJewL6ZrBRWw8PNjQLYAoN5FCcvBjx69sLK","redirectUri":"http://localhost:4200/redirect","resource":"http://example.com/","scope":"openid offline_access webid ","sessionUid":"1_NjytH4OHR2JWeXKptO7","kind":"AuthorizationCode","jti":"q-txnZcaFNmL8ztjR3ptYwEvuDt9AZkS0yDjXmfgiti","clientId":"http://localhost:4200/id-local.jsonld","consumed":1722800477}}}