{"key":"idp/adapter/AuthorizationCode/tU3SVMAt6mNVGglR0Fr-xiwtj8t2Ma_nhXSKsZZBP0A","payload":{"payload":{"iat":1721155358,"exp":1721155958,"accountId":"http://localhost:3000/yori/profile/card#me","authTime":1721154991,"codeChallenge":"VK_jlGl0RtBkIopRRUx_t5YczaFkQ5aYJoFywsdTBQ0","codeChallengeMethod":"S256","grantId":"smVP1LATqsiAn3tn16vTa2zXe4RlKlFKiQ8hJ-syF9s","redirectUri":"http://localhost:4500/redirect","resource":"http://example.com/","scope":"openid webid ","sessionUid":"5a3ED0R-aPD9XPFL9UmQQ","kind":"AuthorizationCode","jti":"tU3SVMAt6mNVGglR0Fr-xiwtj8t2Ma_nhXSKsZZBP0A","clientId":"http://localhost:3000/acme/projectron/vue","expiresWithSession":true,"consumed":1721155358}}}