{"key":"idp/adapter/AuthorizationCode/v1nmTtYgwsKlJrWq_PheeYlLXUIhhLbEKvLZvi8wgar","payload":{"payload":{"iat":1721673400,"exp":1721674000,"accountId":"http://localhost:3000/alice/profile/card#me","authTime":1721670382,"codeChallenge":"A0REHJTSH6krHNCqCaAkt1EhSCm5XD-sToV4B241aV8","codeChallengeMethod":"S256","grantId":"RnyTDXELfApSCqkewZbFotuji261Bra58bW3dqEZpQO","redirectUri":"http://localhost:4500/redirect","resource":"http://example.com/","scope":"openid webid ","sessionUid":"j6CwEOZPJI2kU7mKFcKTF","kind":"AuthorizationCode","jti":"v1nmTtYgwsKlJrWq_PheeYlLXUIhhLbEKvLZvi8wgar","clientId":"http://localhost:3000/acme/projectron/vue","expiresWithSession":true,"consumed":1721673402}}}