{"key":"idp/adapter/AuthorizationCode/zgQZLpc2g9SCG0JxLHc8g3zk2k9sYvPniActkNQhVhg","payload":{"payload":{"iat":1712263873,"exp":1712264473,"accountId":"http://localhost:3000/alice/profile/card#me","authTime":1712263873,"codeChallenge":"t6Y1V-7YifoKWMxC3Mucqi-RoeNJ5go4GlouyCbyyqg","codeChallengeMethod":"S256","grantId":"L2FmYZLGiUMrhhhQj79eAedv9GishtCP1Sdc3Fsf_qI","redirectUri":"http://localhost:4200/redirect","resource":"http://example.com/","scope":"openid offline_access webid ","sessionUid":"Cvl1AT_OB8xm2OIMwvxsu","kind":"AuthorizationCode","jti":"zgQZLpc2g9SCG0JxLHc8g3zk2k9sYvPniActkNQhVhg","clientId":"http://localhost:4200/id-local.jsonld","consumed":1712263873}}}